---
layout: post
title: JVM iinc(自增)
pid: 577
tags: [java]

---

```java
public class Test {
    public static void main(String[] args) {
        int m = 10;
        int n = m++ + ++m + m--;
        System.out.println(m);
        System.out.println(n);
    }
}


```


```java
/Library/Java/JavaVirtualMachines/jdk1.8.0_291.jdk/Contents/Home\bin\javap -v Test
Classfile /Users/baoguo/codes/demo/target/classes/Test.class
  Last modified Mar 26, 2022; size 579 bytes
  MD5 checksum 3c04b521e2739eb126ba6a5ac584a73a
  Compiled from "Test.java"
public class Test
  minor version: 0
  major version: 52
  flags: ACC_PUBLIC, ACC_SUPER
Constant pool:
   #1 = Methodref          #5.#23         // java/lang/Object."<init>":()V
   #2 = Fieldref           #24.#25        // java/lang/System.out:Ljava/io/PrintStream;
   #3 = Methodref          #26.#27        // java/io/PrintStream.println:(I)V
   #4 = Class              #28            // Test
   #5 = Class              #29            // java/lang/Object
   #6 = Utf8               <init>
   #7 = Utf8               ()V
   #8 = Utf8               Code
   #9 = Utf8               LineNumberTable
  #10 = Utf8               LocalVariableTable
  #11 = Utf8               this
  #12 = Utf8               LTest;
  #13 = Utf8               main
  #14 = Utf8               ([Ljava/lang/String;)V
  #15 = Utf8               args
  #16 = Utf8               [Ljava/lang/String;
  #17 = Utf8               m
  #18 = Utf8               I
  #19 = Utf8               n
  #20 = Utf8               MethodParameters
  #21 = Utf8               SourceFile
  #22 = Utf8               Test.java
  #23 = NameAndType        #6:#7          // "<init>":()V
  #24 = Class              #30            // java/lang/System
  #25 = NameAndType        #31:#32        // out:Ljava/io/PrintStream;
  #26 = Class              #33            // java/io/PrintStream
  #27 = NameAndType        #34:#35        // println:(I)V
  #28 = Utf8               Test
  #29 = Utf8               java/lang/Object
  #30 = Utf8               java/lang/System
  #31 = Utf8               out
  #32 = Utf8               Ljava/io/PrintStream;
  #33 = Utf8               java/io/PrintStream
  #34 = Utf8               println
  #35 = Utf8               (I)V
{
  public Test();
    descriptor: ()V
    flags: ACC_PUBLIC
    Code:
      stack=1, locals=1, args_size=1
         0: aload_0
         1: invokespecial #1                  // Method java/lang/Object."<init>":()V
         4: return
      LineNumberTable:
        line 1: 0
      LocalVariableTable:
        Start  Length  Slot  Name   Signature
            0       5     0  this   LTest;

  public static void main(java.lang.String[]);
    descriptor: ([Ljava/lang/String;)V
    flags: ACC_PUBLIC, ACC_STATIC
    Code:
      stack=2, locals=3, args_size=1
         0: bipush        10
         2: istore_1
         3: iload_1
         4: iinc          1, 1
         7: iinc          1, 1
        10: iload_1
        11: iadd
        12: iload_1
        13: iinc          1, -1
        16: iadd
        17: istore_2
        18: getstatic     #2                  // Field java/lang/System.out:Ljava/io/PrintStream;
        21: iload_1
        22: invokevirtual #3                  // Method java/io/PrintStream.println:(I)V
        25: getstatic     #2                  // Field java/lang/System.out:Ljava/io/PrintStream;
        28: iload_2
        29: invokevirtual #3                  // Method java/io/PrintStream.println:(I)V
        32: return
      LineNumberTable:
        line 3: 0
        line 4: 3
        line 5: 18
        line 6: 25
        line 7: 32
      LocalVariableTable:
        Start  Length  Slot  Name   Signature
            0      33     0  args   [Ljava/lang/String;
            3      30     1     m   I
           18      15     2     n   I
    MethodParameters:
      Name                           Flags
      args
}
SourceFile: "Test.java"

Process finished with exit code 0

```









