---
layout: post
title: JVM Program Counter Register(程序计数器)
pid: 571
tags: [java]

---

```java
public class Test {
        public static void main(String[] args) {
                System.out.println(1);
                System.out.println(2);
                System.out.println(3);
                System.out.println(4);
        }
}
```

```java
Compiled from "Test.java"
public class Test {
  public Test();
    Code:
       0: aload_0
       1: invokespecial #1                  // Method java/lang/Object."<init>":()V
       4: return

  public static void main(java.lang.String[]);
    Code:
       0: getstatic     #2                  // Field java/lang/System.out:Ljava/io/PrintStream;
       3: iconst_1
       4: invokevirtual #3                  // Method java/io/PrintStream.println:(I)V
       7: getstatic     #2                  // Field java/lang/System.out:Ljava/io/PrintStream;
      10: iconst_2
      11: invokevirtual #3                  // Method java/io/PrintStream.println:(I)V
      14: getstatic     #2                  // Field java/lang/System.out:Ljava/io/PrintStream;
      17: iconst_3
      18: invokevirtual #3                  // Method java/io/PrintStream.println:(I)V
      21: getstatic     #2                  // Field java/lang/System.out:Ljava/io/PrintStream;
      24: iconst_4
      25: invokevirtual #3                  // Method java/io/PrintStream.println:(I)V
      28: return
}
```






# 参考
+ [01-JVM内存模型：程序计数器 ](https://www.cnblogs.com/manayi/p/9290490.html)